odk2stata/__init__.py
odk2stata/__main__.py
odk2stata/__version__.py
odk2stata/dataset/__init__.py
odk2stata/dataset/column.py
odk2stata/dataset/dataset.py
odk2stata/dataset/dataset_collection.py
odk2stata/dataset/utils.py
odk2stata/dofile/__init__.py
odk2stata/dofile/cli.py
odk2stata/dofile/destring.py
odk2stata/dofile/do_file.py
odk2stata/dofile/do_file_collection.py
odk2stata/dofile/do_file_section.py
odk2stata/dofile/drop_column.py
odk2stata/dofile/encode_select_one.py
odk2stata/dofile/imported_dataset.py
odk2stata/dofile/label_variable.py
odk2stata/dofile/metadata.py
odk2stata/dofile/rename.py
odk2stata/dofile/split_select_multiple.py
odk2stata/dofile/stata_utils.py
odk2stata/dofile/varname_manager.py
odk2stata/dofile/settings/__init__.py
odk2stata/dofile/settings/__main__.py
odk2stata/dofile/settings/cli.py
odk2stata/dofile/settings/settings_manager.py
odk2stata/dofile/templates/__init__.py
odk2stata/dofile/templates/base.do
odk2stata/dofile/templates/cleaning.do
odk2stata/dofile/templates/destring.do
odk2stata/dofile/templates/drop_column.do
odk2stata/dofile/templates/encode_select_one.do
odk2stata/dofile/templates/encode_select_one_for_unit.do
odk2stata/dofile/templates/encode_select_one_unit.do
odk2stata/dofile/templates/label_define_unit.do
odk2stata/dofile/templates/label_variable.do
odk2stata/dofile/templates/macros.do
odk2stata/dofile/templates/rename.do
odk2stata/dofile/templates/rename_odk_name_sect.do
odk2stata/dofile/templates/split_select_multiple.do
odk2stata/dofile/templates/split_select_multiple_unit.do
odk2stata/error/__init__.py
odk2stata/gui/__init__.py
odk2stata/gui/__main__.py
odk2stata/gui/gui.py
odk2stata/gui/worker.py
odk2stata/odkform/__init__.py
odk2stata/odkform/choices.py
odk2stata/odkform/components.py
odk2stata/odkform/odkform.py
odk2stata/odkform/settings.py
odk2stata/odkform/survey.py
odk2stata-0.2.6.dist-info/LICENSE.txt
odk2stata-0.2.6.dist-info/METADATA
odk2stata-0.2.6.dist-info/WHEEL
odk2stata-0.2.6.dist-info/entry_points.txt
odk2stata-0.2.6.dist-info/top_level.txt
odk2stata-0.2.6.dist-info/RECORD
