Metadata-Version: 2.1
Name: odk2stata
Version: 0.2.6
Summary: Generate a Stata do file for ODK analysis.
Home-page: https://github.com/jkpr/odk2stata
Author: James Pringle
Author-email: jpringle@jhu.edu
License: MIT
Platform: UNKNOWN
Classifier: License :: OSI Approved :: MIT License
Classifier: Programming Language :: Python
Classifier: Programming Language :: Python :: 3
Classifier: Programming Language :: Python :: 3.7
Classifier: Programming Language :: Python :: Implementation :: CPython
Requires-Python: >=3.7.0
Requires-Dist: xlrd (<=2.0.0)
Requires-Dist: Jinja2 (>=2.10)
Provides-Extra: gui
Requires-Dist: wxpython ; extra == 'gui'
